anek_process/__init__.py
anek_process/multiproc.py
anek_process/utils/__init__.py
anek_process/utils/logger.py
anek_process-0.0.7.dist-info/LICENSE.md
anek_process-0.0.7.dist-info/METADATA
anek_process-0.0.7.dist-info/WHEEL
anek_process-0.0.7.dist-info/top_level.txt
anek_process-0.0.7.dist-info/RECORD
