Metadata-Version: 2.1
Name: anek-process
Version: 0.0.7
Summary: Parallel processing of tasks for vertical scaling
Author: Bhramaand (Lalit Atrish)
Author-email: <atrish.lalit03@gmail.com>
Keywords: python,parallel,processing,thread,threading,veritcal,scaling
Classifier: Development Status :: 1 - Planning
Classifier: Intended Audience :: Developers
Classifier: Programming Language :: Python :: 3
Classifier: Operating System :: Unix
Classifier: Operating System :: MacOS :: MacOS X
Classifier: Operating System :: Microsoft :: Windows
License-File: LICENSE.md
